{
  "location": "KBOS",
  "forecast_date": "2026-05-11",
  "target_date": "2026-05-12",
  "lead_time_days": 1,
  "open_meteo": {
    "temp_high": 55.1,
    "temp_low": 42.1,
    "precip": 0.0
  },
  "nws": [
    {
      "name": "Overnight",
      "temperature": 46,
      "temperatureUnit": "F",
      "temperatureTrend": null,
      "probabilityOfPrecipitation": 28,
      "dewpoint": null,
      "relativeHumidity": null,
      "windSpeed": "6 mph",
      "windDirection": "NW",
      "shortForecast": "Chance Rain Showers",
      "detailedForecast": "A chance of rain showers. Mostly cloudy, with a low around 46. Northwest wind around 6 mph. Chance of precipitation is 30%.",
      "isDaytime": false,
      "startTime": "2026-05-11T03:00:00-04:00",
      "endTime": "2026-05-11T06:00:00-04:00"
    },
    {
      "name": "Monday",
      "temperature": 63,
      "temperatureUnit": "F",
      "temperatureTrend": null,
      "probabilityOfPrecipitation": 16,
      "dewpoint": null,
      "relativeHumidity": null,
      "windSpeed": "6 mph",
      "windDirection": "NW",
      "shortForecast": "Slight Chance Rain Showers then Partly Sunny",
      "detailedForecast": "A slight chance of rain showers before 9am. Partly sunny, with a high near 63. Northwest wind around 6 mph. Chance of precipitation is 20%.",
      "isDaytime": true,
      "startTime": "2026-05-11T06:00:00-04:00",
      "endTime": "2026-05-11T18:00:00-04:00"
    },
    {
      "name": "Monday Night",
      "temperature": 43,
      "temperatureUnit": "F",
      "temperatureTrend": null,
      "probabilityOfPrecipitation": 4,
      "dewpoint": null,
      "relativeHumidity": null,
      "windSpeed": "6 mph",
      "windDirection": "NW",
      "shortForecast": "Partly Cloudy",
      "detailedForecast": "Partly cloudy, with a low around 43. Northwest wind around 6 mph.",
      "isDaytime": false,
      "startTime": "2026-05-11T18:00:00-04:00",
      "endTime": "2026-05-12T06:00:00-04:00"
    },
    {
      "name": "Tuesday",
      "temperature": 62,
      "temperatureUnit": "F",
      "temperatureTrend": null,
      "probabilityOfPrecipitation": 4,
      "dewpoint": null,
      "relativeHumidity": null,
      "windSpeed": "7 mph",
      "windDirection": "NW",
      "shortForecast": "Mostly Sunny",
      "detailedForecast": "Mostly sunny, with a high near 62. Northwest wind around 7 mph.",
      "isDaytime": true,
      "startTime": "2026-05-12T06:00:00-04:00",
      "endTime": "2026-05-12T18:00:00-04:00"
    },
    {
      "name": "Tuesday Night",
      "temperature": 43,
      "temperatureUnit": "F",
      "temperatureTrend": null,
      "probabilityOfPrecipitation": 0,
      "dewpoint": null,
      "relativeHumidity": null,
      "windSpeed": "5 mph",
      "windDirection": "W",
      "shortForecast": "Partly Cloudy",
      "detailedForecast": "Partly cloudy, with a low around 43. West wind around 5 mph.",
      "isDaytime": false,
      "startTime": "2026-05-12T18:00:00-04:00",
      "endTime": "2026-05-13T06:00:00-04:00"
    },
    {
      "name": "Wednesday",
      "temperature": 61,
      "temperatureUnit": "F",
      "temperatureTrend": null,
      "probabilityOfPrecipitation": 25,
      "dewpoint": null,
      "relativeHumidity": null,
      "windSpeed": "2 to 13 mph",
      "windDirection": "S",
      "shortForecast": "Mostly Cloudy then Chance Rain Showers",
      "detailedForecast": "A chance of rain showers after 2pm. Mostly cloudy, with a high near 61. South wind 2 to 13 mph, with gusts as high as 23 mph. Chance of precipitation is 30%.",
      "isDaytime": true,
      "startTime": "2026-05-13T06:00:00-04:00",
      "endTime": "2026-05-13T18:00:00-04:00"
    },
    {
      "name": "Wednesday Night",
      "temperature": 47,
      "temperatureUnit": "F",
      "temperatureTrend": null,
      "probabilityOfPrecipitation": 77,
      "dewpoint": null,
      "relativeHumidity": null,
      "windSpeed": "12 mph",
      "windDirection": "S",
      "shortForecast": "Rain Showers",
      "detailedForecast": "A chance of rain showers before 11pm, then rain showers and patchy fog. Cloudy, with a low around 47. South wind around 12 mph, with gusts as high as 22 mph. Chance of precipitation is 80%.",
      "isDaytime": false,
      "startTime": "2026-05-13T18:00:00-04:00",
      "endTime": "2026-05-14T06:00:00-04:00"
    },
    {
      "name": "Thursday",
      "temperature": 62,
      "temperatureUnit": "F",
      "temperatureTrend": null,
      "probabilityOfPrecipitation": 92,
      "dewpoint": null,
      "relativeHumidity": null,
      "windSpeed": "10 mph",
      "windDirection": "S",
      "shortForecast": "Rain Showers",
      "detailedForecast": "Rain showers and patchy fog. Cloudy, with a high near 62. South wind around 10 mph. Chance of precipitation is 90%.",
      "isDaytime": true,
      "startTime": "2026-05-14T06:00:00-04:00",
      "endTime": "2026-05-14T18:00:00-04:00"
    },
    {
      "name": "Thursday Night",
      "temperature": 47,
      "temperatureUnit": "F",
      "temperatureTrend": null,
      "probabilityOfPrecipitation": 66,
      "dewpoint": null,
      "relativeHumidity": null,
      "windSpeed": "3 to 8 mph",
      "windDirection": "W",
      "shortForecast": "Rain Showers Likely",
      "detailedForecast": "Rain showers likely. Mostly cloudy, with a low around 47. West wind 3 to 8 mph. Chance of precipitation is 70%.",
      "isDaytime": false,
      "startTime": "2026-05-14T18:00:00-04:00",
      "endTime": "2026-05-15T06:00:00-04:00"
    },
    {
      "name": "Friday",
      "temperature": 64,
      "temperatureUnit": "F",
      "temperatureTrend": null,
      "probabilityOfPrecipitation": 45,
      "dewpoint": null,
      "relativeHumidity": null,
      "windSpeed": "3 to 8 mph",
      "windDirection": "N",
      "shortForecast": "Chance Rain Showers",
      "detailedForecast": "A chance of rain showers. Partly sunny, with a high near 64. North wind 3 to 8 mph. Chance of precipitation is 50%.",
      "isDaytime": true,
      "startTime": "2026-05-15T06:00:00-04:00",
      "endTime": "2026-05-15T18:00:00-04:00"
    },
    {
      "name": "Friday Night",
      "temperature": 49,
      "temperatureUnit": "F",
      "temperatureTrend": null,
      "probabilityOfPrecipitation": 41,
      "dewpoint": null,
      "relativeHumidity": null,
      "windSpeed": "3 to 7 mph",
      "windDirection": "NW",
      "shortForecast": "Chance Rain Showers",
      "detailedForecast": "A chance of rain showers. Partly cloudy, with a low around 49. Northwest wind 3 to 7 mph. Chance of precipitation is 40%.",
      "isDaytime": false,
      "startTime": "2026-05-15T18:00:00-04:00",
      "endTime": "2026-05-16T06:00:00-04:00"
    },
    {
      "name": "Saturday",
      "temperature": 72,
      "temperatureUnit": "F",
      "temperatureTrend": null,
      "probabilityOfPrecipitation": 17,
      "dewpoint": null,
      "relativeHumidity": null,
      "windSpeed": "6 to 9 mph",
      "windDirection": "W",
      "shortForecast": "Slight Chance Rain Showers then Mostly Sunny",
      "detailedForecast": "A slight chance of rain showers before 8am. Mostly sunny, with a high near 72. West wind 6 to 9 mph.",
      "isDaytime": true,
      "startTime": "2026-05-16T06:00:00-04:00",
      "endTime": "2026-05-16T18:00:00-04:00"
    },
    {
      "name": "Saturday Night",
      "temperature": 52,
      "temperatureUnit": "F",
      "temperatureTrend": null,
      "probabilityOfPrecipitation": 7,
      "dewpoint": null,
      "relativeHumidity": null,
      "windSpeed": "7 mph",
      "windDirection": "SW",
      "shortForecast": "Partly Cloudy",
      "detailedForecast": "Partly cloudy, with a low around 52. Southwest wind around 7 mph.",
      "isDaytime": false,
      "startTime": "2026-05-16T18:00:00-04:00",
      "endTime": "2026-05-17T06:00:00-04:00"
    },
    {
      "name": "Sunday",
      "temperature": 75,
      "temperatureUnit": "F",
      "temperatureTrend": null,
      "probabilityOfPrecipitation": 7,
      "dewpoint": null,
      "relativeHumidity": null,
      "windSpeed": "5 to 9 mph",
      "windDirection": "W",
      "shortForecast": "Mostly Sunny",
      "detailedForecast": "Mostly sunny, with a high near 75. West wind 5 to 9 mph.",
      "isDaytime": true,
      "startTime": "2026-05-17T06:00:00-04:00",
      "endTime": "2026-05-17T18:00:00-04:00"
    }
  ]
}