{
  "location": "KDEN",
  "forecast_date": "2026-07-03",
  "target_date": "2026-07-04",
  "lead_time_days": 1,
  "open_meteo": {
    "temp_high": 87.5,
    "temp_low": 61.7,
    "precip": 0.169
  },
  "nws": [
    {
      "name": "Overnight",
      "temperature": 58,
      "temperatureUnit": "F",
      "temperatureTrend": null,
      "probabilityOfPrecipitation": 15,
      "dewpoint": null,
      "relativeHumidity": null,
      "windSpeed": "7 mph",
      "windDirection": "WSW",
      "shortForecast": "Slight Chance Rain Showers",
      "detailedForecast": "A slight chance of rain showers before 2am, then patchy smoke. Mostly clear. Low around 58, with temperatures rising to around 60 overnight. West southwest wind around 7 mph. Chance of precipitation is 20%.",
      "isDaytime": false,
      "startTime": "2026-07-03T01:00:00-06:00",
      "endTime": "2026-07-03T06:00:00-06:00"
    },
    {
      "name": "Friday",
      "temperature": 93,
      "temperatureUnit": "F",
      "temperatureTrend": null,
      "probabilityOfPrecipitation": 1,
      "dewpoint": null,
      "relativeHumidity": null,
      "windSpeed": "5 to 8 mph",
      "windDirection": "N",
      "shortForecast": "Patchy Smoke then Sunny",
      "detailedForecast": "Patchy smoke before noon. Sunny. High near 93, with temperatures falling to around 91 in the afternoon. North wind 5 to 8 mph, with gusts as high as 17 mph.",
      "isDaytime": true,
      "startTime": "2026-07-03T06:00:00-06:00",
      "endTime": "2026-07-03T18:00:00-06:00"
    },
    {
      "name": "Friday Night",
      "temperature": 59,
      "temperatureUnit": "F",
      "temperatureTrend": null,
      "probabilityOfPrecipitation": 3,
      "dewpoint": null,
      "relativeHumidity": null,
      "windSpeed": "5 to 12 mph",
      "windDirection": "NNW",
      "shortForecast": "Partly Cloudy",
      "detailedForecast": "Partly cloudy. Low around 59, with temperatures rising to around 62 overnight. North northwest wind 5 to 12 mph, with gusts as high as 18 mph.",
      "isDaytime": false,
      "startTime": "2026-07-03T18:00:00-06:00",
      "endTime": "2026-07-04T06:00:00-06:00"
    },
    {
      "name": "Independence Day",
      "temperature": 90,
      "temperatureUnit": "F",
      "temperatureTrend": null,
      "probabilityOfPrecipitation": 26,
      "dewpoint": null,
      "relativeHumidity": null,
      "windSpeed": "3 to 9 mph",
      "windDirection": "E",
      "shortForecast": "Mostly Sunny then Chance Showers And Thunderstorms",
      "detailedForecast": "A chance of showers and thunderstorms after 3pm. Mostly sunny, with a high near 90. East wind 3 to 9 mph, with gusts as high as 18 mph. Chance of precipitation is 30%.",
      "isDaytime": true,
      "startTime": "2026-07-04T06:00:00-06:00",
      "endTime": "2026-07-04T18:00:00-06:00"
    },
    {
      "name": "Saturday Night",
      "temperature": 59,
      "temperatureUnit": "F",
      "temperatureTrend": null,
      "probabilityOfPrecipitation": 12,
      "dewpoint": null,
      "relativeHumidity": null,
      "windSpeed": "6 to 10 mph",
      "windDirection": "SE",
      "shortForecast": "Partly Cloudy",
      "detailedForecast": "Partly cloudy, with a low around 59. Southeast wind 6 to 10 mph, with gusts as high as 18 mph.",
      "isDaytime": false,
      "startTime": "2026-07-04T18:00:00-06:00",
      "endTime": "2026-07-05T06:00:00-06:00"
    },
    {
      "name": "Sunday",
      "temperature": 92,
      "temperatureUnit": "F",
      "temperatureTrend": null,
      "probabilityOfPrecipitation": 33,
      "dewpoint": null,
      "relativeHumidity": null,
      "windSpeed": "3 to 15 mph",
      "windDirection": "S",
      "shortForecast": "Sunny then Chance Showers And Thunderstorms",
      "detailedForecast": "A chance of showers and thunderstorms between noon and 3pm, then a chance of showers and thunderstorms. Sunny, with a high near 92. Chance of precipitation is 30%.",
      "isDaytime": true,
      "startTime": "2026-07-05T06:00:00-06:00",
      "endTime": "2026-07-05T18:00:00-06:00"
    },
    {
      "name": "Sunday Night",
      "temperature": 62,
      "temperatureUnit": "F",
      "temperatureTrend": null,
      "probabilityOfPrecipitation": 5,
      "dewpoint": null,
      "relativeHumidity": null,
      "windSpeed": "8 to 17 mph",
      "windDirection": "S",
      "shortForecast": "Partly Cloudy",
      "detailedForecast": "Partly cloudy, with a low around 62.",
      "isDaytime": false,
      "startTime": "2026-07-05T18:00:00-06:00",
      "endTime": "2026-07-06T06:00:00-06:00"
    },
    {
      "name": "Monday",
      "temperature": 93,
      "temperatureUnit": "F",
      "temperatureTrend": null,
      "probabilityOfPrecipitation": 13,
      "dewpoint": null,
      "relativeHumidity": null,
      "windSpeed": "3 to 10 mph",
      "windDirection": "W",
      "shortForecast": "Mostly Sunny",
      "detailedForecast": "Mostly sunny, with a high near 93.",
      "isDaytime": true,
      "startTime": "2026-07-06T06:00:00-06:00",
      "endTime": "2026-07-06T18:00:00-06:00"
    },
    {
      "name": "Monday Night",
      "temperature": 62,
      "temperatureUnit": "F",
      "temperatureTrend": null,
      "probabilityOfPrecipitation": 18,
      "dewpoint": null,
      "relativeHumidity": null,
      "windSpeed": "9 to 16 mph",
      "windDirection": "SSE",
      "shortForecast": "Slight Chance Showers And Thunderstorms then Mostly Cloudy",
      "detailedForecast": "A slight chance of showers and thunderstorms before midnight. Mostly cloudy, with a low around 62.",
      "isDaytime": false,
      "startTime": "2026-07-06T18:00:00-06:00",
      "endTime": "2026-07-07T06:00:00-06:00"
    },
    {
      "name": "Tuesday",
      "temperature": 92,
      "temperatureUnit": "F",
      "temperatureTrend": null,
      "probabilityOfPrecipitation": 37,
      "dewpoint": null,
      "relativeHumidity": null,
      "windSpeed": "5 to 10 mph",
      "windDirection": "SSE",
      "shortForecast": "Partly Sunny then Chance Showers And Thunderstorms",
      "detailedForecast": "A chance of showers and thunderstorms after noon. Partly sunny, with a high near 92.",
      "isDaytime": true,
      "startTime": "2026-07-07T06:00:00-06:00",
      "endTime": "2026-07-07T18:00:00-06:00"
    },
    {
      "name": "Tuesday Night",
      "temperature": 62,
      "temperatureUnit": "F",
      "temperatureTrend": null,
      "probabilityOfPrecipitation": 23,
      "dewpoint": null,
      "relativeHumidity": null,
      "windSpeed": "7 to 10 mph",
      "windDirection": "SSE",
      "shortForecast": "Slight Chance Showers And Thunderstorms then Partly Cloudy",
      "detailedForecast": "A slight chance of showers and thunderstorms before midnight. Partly cloudy, with a low around 62.",
      "isDaytime": false,
      "startTime": "2026-07-07T18:00:00-06:00",
      "endTime": "2026-07-08T06:00:00-06:00"
    },
    {
      "name": "Wednesday",
      "temperature": 94,
      "temperatureUnit": "F",
      "temperatureTrend": null,
      "probabilityOfPrecipitation": 23,
      "dewpoint": null,
      "relativeHumidity": null,
      "windSpeed": "6 to 10 mph",
      "windDirection": "NW",
      "shortForecast": "Mostly Sunny then Slight Chance Showers And Thunderstorms",
      "detailedForecast": "A slight chance of showers and thunderstorms after noon. Mostly sunny, with a high near 94.",
      "isDaytime": true,
      "startTime": "2026-07-08T06:00:00-06:00",
      "endTime": "2026-07-08T18:00:00-06:00"
    },
    {
      "name": "Wednesday Night",
      "temperature": 62,
      "temperatureUnit": "F",
      "temperatureTrend": null,
      "probabilityOfPrecipitation": 16,
      "dewpoint": null,
      "relativeHumidity": null,
      "windSpeed": "7 to 12 mph",
      "windDirection": "S",
      "shortForecast": "Slight Chance Showers And Thunderstorms then Partly Cloudy",
      "detailedForecast": "A slight chance of showers and thunderstorms before midnight. Partly cloudy, with a low around 62.",
      "isDaytime": false,
      "startTime": "2026-07-08T18:00:00-06:00",
      "endTime": "2026-07-09T06:00:00-06:00"
    },
    {
      "name": "Thursday",
      "temperature": 94,
      "temperatureUnit": "F",
      "temperatureTrend": null,
      "probabilityOfPrecipitation": 22,
      "dewpoint": null,
      "relativeHumidity": null,
      "windSpeed": "6 to 10 mph",
      "windDirection": "WNW",
      "shortForecast": "Mostly Sunny then Slight Chance Showers And Thunderstorms",
      "detailedForecast": "A slight chance of showers and thunderstorms after noon. Mostly sunny, with a high near 94.",
      "isDaytime": true,
      "startTime": "2026-07-09T06:00:00-06:00",
      "endTime": "2026-07-09T18:00:00-06:00"
    }
  ]
}