{
  "location": "KDEN",
  "forecast_date": "2026-03-24",
  "target_date": "2026-03-25",
  "lead_time_days": 1,
  "open_meteo": {
    "temp_high": 86.9,
    "temp_low": 52.7,
    "precip": 0.0
  },
  "nws": [
    {
      "name": "Overnight",
      "temperature": 47,
      "temperatureUnit": "F",
      "temperatureTrend": null,
      "probabilityOfPrecipitation": 0,
      "dewpoint": null,
      "relativeHumidity": null,
      "windSpeed": "8 mph",
      "windDirection": "SSW",
      "shortForecast": "Mostly Cloudy",
      "detailedForecast": "Mostly cloudy, with a low around 47. South southwest wind around 8 mph.",
      "isDaytime": false,
      "startTime": "2026-03-24T01:00:00-06:00",
      "endTime": "2026-03-24T06:00:00-06:00"
    },
    {
      "name": "Tuesday",
      "temperature": 80,
      "temperatureUnit": "F",
      "temperatureTrend": null,
      "probabilityOfPrecipitation": 0,
      "dewpoint": null,
      "relativeHumidity": null,
      "windSpeed": "6 to 13 mph",
      "windDirection": "WSW",
      "shortForecast": "Mostly Sunny",
      "detailedForecast": "Mostly sunny, with a high near 80. West southwest wind 6 to 13 mph, with gusts as high as 21 mph.",
      "isDaytime": true,
      "startTime": "2026-03-24T06:00:00-06:00",
      "endTime": "2026-03-24T18:00:00-06:00"
    },
    {
      "name": "Tuesday Night",
      "temperature": 54,
      "temperatureUnit": "F",
      "temperatureTrend": null,
      "probabilityOfPrecipitation": 0,
      "dewpoint": null,
      "relativeHumidity": null,
      "windSpeed": "6 to 12 mph",
      "windDirection": "W",
      "shortForecast": "Mostly Clear",
      "detailedForecast": "Mostly clear, with a low around 54. West wind 6 to 12 mph, with gusts as high as 18 mph.",
      "isDaytime": false,
      "startTime": "2026-03-24T18:00:00-06:00",
      "endTime": "2026-03-25T06:00:00-06:00"
    },
    {
      "name": "Wednesday",
      "temperature": 88,
      "temperatureUnit": "F",
      "temperatureTrend": null,
      "probabilityOfPrecipitation": 4,
      "dewpoint": null,
      "relativeHumidity": null,
      "windSpeed": "7 to 12 mph",
      "windDirection": "SW",
      "shortForecast": "Sunny",
      "detailedForecast": "Sunny, with a high near 88. Southwest wind 7 to 12 mph, with gusts as high as 21 mph.",
      "isDaytime": true,
      "startTime": "2026-03-25T06:00:00-06:00",
      "endTime": "2026-03-25T18:00:00-06:00"
    },
    {
      "name": "Wednesday Night",
      "temperature": 53,
      "temperatureUnit": "F",
      "temperatureTrend": null,
      "probabilityOfPrecipitation": 11,
      "dewpoint": null,
      "relativeHumidity": null,
      "windSpeed": "7 to 10 mph",
      "windDirection": "SSW",
      "shortForecast": "Mostly Clear",
      "detailedForecast": "Mostly clear, with a low around 53. South southwest wind 7 to 10 mph, with gusts as high as 18 mph.",
      "isDaytime": false,
      "startTime": "2026-03-25T18:00:00-06:00",
      "endTime": "2026-03-26T06:00:00-06:00"
    },
    {
      "name": "Thursday",
      "temperature": 76,
      "temperatureUnit": "F",
      "temperatureTrend": null,
      "probabilityOfPrecipitation": 8,
      "dewpoint": null,
      "relativeHumidity": null,
      "windSpeed": "7 to 20 mph",
      "windDirection": "NNW",
      "shortForecast": "Mostly Sunny",
      "detailedForecast": "Mostly sunny, with a high near 76.",
      "isDaytime": true,
      "startTime": "2026-03-26T06:00:00-06:00",
      "endTime": "2026-03-26T18:00:00-06:00"
    },
    {
      "name": "Thursday Night",
      "temperature": 36,
      "temperatureUnit": "F",
      "temperatureTrend": null,
      "probabilityOfPrecipitation": 22,
      "dewpoint": null,
      "relativeHumidity": null,
      "windSpeed": "10 to 20 mph",
      "windDirection": "ENE",
      "shortForecast": "Slight Chance Light Rain then Mostly Cloudy",
      "detailedForecast": "A slight chance of rain before midnight. Mostly cloudy, with a low around 36.",
      "isDaytime": false,
      "startTime": "2026-03-26T18:00:00-06:00",
      "endTime": "2026-03-27T06:00:00-06:00"
    },
    {
      "name": "Friday",
      "temperature": 57,
      "temperatureUnit": "F",
      "temperatureTrend": null,
      "probabilityOfPrecipitation": 8,
      "dewpoint": null,
      "relativeHumidity": null,
      "windSpeed": "10 to 17 mph",
      "windDirection": "ESE",
      "shortForecast": "Partly Sunny",
      "detailedForecast": "Partly sunny, with a high near 57.",
      "isDaytime": true,
      "startTime": "2026-03-27T06:00:00-06:00",
      "endTime": "2026-03-27T18:00:00-06:00"
    },
    {
      "name": "Friday Night",
      "temperature": 37,
      "temperatureUnit": "F",
      "temperatureTrend": null,
      "probabilityOfPrecipitation": 3,
      "dewpoint": null,
      "relativeHumidity": null,
      "windSpeed": "10 to 18 mph",
      "windDirection": "SSE",
      "shortForecast": "Mostly Cloudy",
      "detailedForecast": "Mostly cloudy, with a low around 37.",
      "isDaytime": false,
      "startTime": "2026-03-27T18:00:00-06:00",
      "endTime": "2026-03-28T06:00:00-06:00"
    },
    {
      "name": "Saturday",
      "temperature": 75,
      "temperatureUnit": "F",
      "temperatureTrend": null,
      "probabilityOfPrecipitation": 7,
      "dewpoint": null,
      "relativeHumidity": null,
      "windSpeed": "7 to 13 mph",
      "windDirection": "SE",
      "shortForecast": "Partly Sunny",
      "detailedForecast": "Partly sunny, with a high near 75.",
      "isDaytime": true,
      "startTime": "2026-03-28T06:00:00-06:00",
      "endTime": "2026-03-28T18:00:00-06:00"
    },
    {
      "name": "Saturday Night",
      "temperature": 47,
      "temperatureUnit": "F",
      "temperatureTrend": null,
      "probabilityOfPrecipitation": 9,
      "dewpoint": null,
      "relativeHumidity": null,
      "windSpeed": "8 to 13 mph",
      "windDirection": "SW",
      "shortForecast": "Mostly Cloudy",
      "detailedForecast": "Mostly cloudy, with a low around 47.",
      "isDaytime": false,
      "startTime": "2026-03-28T18:00:00-06:00",
      "endTime": "2026-03-29T06:00:00-06:00"
    },
    {
      "name": "Sunday",
      "temperature": 78,
      "temperatureUnit": "F",
      "temperatureTrend": null,
      "probabilityOfPrecipitation": 12,
      "dewpoint": null,
      "relativeHumidity": null,
      "windSpeed": "10 mph",
      "windDirection": "SW",
      "shortForecast": "Partly Sunny",
      "detailedForecast": "Partly sunny, with a high near 78.",
      "isDaytime": true,
      "startTime": "2026-03-29T06:00:00-06:00",
      "endTime": "2026-03-29T18:00:00-06:00"
    },
    {
      "name": "Sunday Night",
      "temperature": 47,
      "temperatureUnit": "F",
      "temperatureTrend": null,
      "probabilityOfPrecipitation": 20,
      "dewpoint": null,
      "relativeHumidity": null,
      "windSpeed": "10 mph",
      "windDirection": "SW",
      "shortForecast": "Slight Chance Light Rain then Mostly Cloudy",
      "detailedForecast": "A slight chance of rain before midnight. Mostly cloudy, with a low around 47.",
      "isDaytime": false,
      "startTime": "2026-03-29T18:00:00-06:00",
      "endTime": "2026-03-30T06:00:00-06:00"
    },
    {
      "name": "Monday",
      "temperature": 77,
      "temperatureUnit": "F",
      "temperatureTrend": null,
      "probabilityOfPrecipitation": 18,
      "dewpoint": null,
      "relativeHumidity": null,
      "windSpeed": "7 to 13 mph",
      "windDirection": "WNW",
      "shortForecast": "Partly Sunny then Slight Chance Light Rain",
      "detailedForecast": "A slight chance of rain after noon. Partly sunny, with a high near 77.",
      "isDaytime": true,
      "startTime": "2026-03-30T06:00:00-06:00",
      "endTime": "2026-03-30T18:00:00-06:00"
    }
  ]
}