{
  "location": "KLAX",
  "forecast_date": "2025-12-11",
  "target_date": "2025-12-12",
  "lead_time_days": 1,
  "open_meteo": {
    "temp_high": 65.9,
    "temp_low": 51.2,
    "precip": 0.0
  },
  "nws": [
    {
      "name": "This Afternoon",
      "temperature": 78,
      "temperatureUnit": "F",
      "temperatureTrend": null,
      "probabilityOfPrecipitation": 0,
      "dewpoint": null,
      "relativeHumidity": null,
      "windSpeed": "5 mph",
      "windDirection": "WNW",
      "shortForecast": "Sunny",
      "detailedForecast": "Sunny, with a high near 78. West northwest wind around 5 mph.",
      "isDaytime": true,
      "startTime": "2025-12-10T17:00:00-08:00",
      "endTime": "2025-12-10T18:00:00-08:00"
    },
    {
      "name": "Tonight",
      "temperature": 55,
      "temperatureUnit": "F",
      "temperatureTrend": null,
      "probabilityOfPrecipitation": 0,
      "dewpoint": null,
      "relativeHumidity": null,
      "windSpeed": "5 mph",
      "windDirection": "NNW",
      "shortForecast": "Mostly Clear",
      "detailedForecast": "Mostly clear, with a low around 55. North northwest wind around 5 mph.",
      "isDaytime": false,
      "startTime": "2025-12-10T18:00:00-08:00",
      "endTime": "2025-12-11T06:00:00-08:00"
    },
    {
      "name": "Thursday",
      "temperature": 73,
      "temperatureUnit": "F",
      "temperatureTrend": null,
      "probabilityOfPrecipitation": 0,
      "dewpoint": null,
      "relativeHumidity": null,
      "windSpeed": "5 mph",
      "windDirection": "WNW",
      "shortForecast": "Sunny",
      "detailedForecast": "Sunny, with a high near 73. West northwest wind around 5 mph.",
      "isDaytime": true,
      "startTime": "2025-12-11T06:00:00-08:00",
      "endTime": "2025-12-11T18:00:00-08:00"
    },
    {
      "name": "Thursday Night",
      "temperature": 55,
      "temperatureUnit": "F",
      "temperatureTrend": null,
      "probabilityOfPrecipitation": 0,
      "dewpoint": null,
      "relativeHumidity": null,
      "windSpeed": "0 to 5 mph",
      "windDirection": "N",
      "shortForecast": "Patchy Fog",
      "detailedForecast": "Patchy fog after 10pm. Mostly cloudy, with a low around 55. North wind 0 to 5 mph.",
      "isDaytime": false,
      "startTime": "2025-12-11T18:00:00-08:00",
      "endTime": "2025-12-12T06:00:00-08:00"
    },
    {
      "name": "Friday",
      "temperature": 72,
      "temperatureUnit": "F",
      "temperatureTrend": null,
      "probabilityOfPrecipitation": 0,
      "dewpoint": null,
      "relativeHumidity": null,
      "windSpeed": "0 to 5 mph",
      "windDirection": "SE",
      "shortForecast": "Patchy Fog then Mostly Sunny",
      "detailedForecast": "Patchy fog before 10am. Mostly sunny, with a high near 72. Southeast wind 0 to 5 mph.",
      "isDaytime": true,
      "startTime": "2025-12-12T06:00:00-08:00",
      "endTime": "2025-12-12T18:00:00-08:00"
    },
    {
      "name": "Friday Night",
      "temperature": 54,
      "temperatureUnit": "F",
      "temperatureTrend": null,
      "probabilityOfPrecipitation": 0,
      "dewpoint": null,
      "relativeHumidity": null,
      "windSpeed": "0 to 5 mph",
      "windDirection": "NNW",
      "shortForecast": "Mostly Cloudy then Patchy Fog",
      "detailedForecast": "Patchy fog after 4am. Mostly cloudy, with a low around 54.",
      "isDaytime": false,
      "startTime": "2025-12-12T18:00:00-08:00",
      "endTime": "2025-12-13T06:00:00-08:00"
    },
    {
      "name": "Saturday",
      "temperature": 69,
      "temperatureUnit": "F",
      "temperatureTrend": null,
      "probabilityOfPrecipitation": 0,
      "dewpoint": null,
      "relativeHumidity": null,
      "windSpeed": "0 to 5 mph",
      "windDirection": "SE",
      "shortForecast": "Patchy Fog then Mostly Sunny",
      "detailedForecast": "Patchy fog before 10am. Mostly sunny, with a high near 69.",
      "isDaytime": true,
      "startTime": "2025-12-13T06:00:00-08:00",
      "endTime": "2025-12-13T18:00:00-08:00"
    },
    {
      "name": "Saturday Night",
      "temperature": 54,
      "temperatureUnit": "F",
      "temperatureTrend": null,
      "probabilityOfPrecipitation": 0,
      "dewpoint": null,
      "relativeHumidity": null,
      "windSpeed": "0 to 5 mph",
      "windDirection": "WNW",
      "shortForecast": "Patchy Fog",
      "detailedForecast": "Patchy fog after 10pm. Mostly cloudy, with a low around 54.",
      "isDaytime": false,
      "startTime": "2025-12-13T18:00:00-08:00",
      "endTime": "2025-12-14T06:00:00-08:00"
    },
    {
      "name": "Sunday",
      "temperature": 65,
      "temperatureUnit": "F",
      "temperatureTrend": null,
      "probabilityOfPrecipitation": 0,
      "dewpoint": null,
      "relativeHumidity": null,
      "windSpeed": "0 to 5 mph",
      "windDirection": "NW",
      "shortForecast": "Patchy Fog then Mostly Sunny",
      "detailedForecast": "Patchy fog before 10am. Mostly sunny, with a high near 65.",
      "isDaytime": true,
      "startTime": "2025-12-14T06:00:00-08:00",
      "endTime": "2025-12-14T18:00:00-08:00"
    },
    {
      "name": "Sunday Night",
      "temperature": 52,
      "temperatureUnit": "F",
      "temperatureTrend": null,
      "probabilityOfPrecipitation": 0,
      "dewpoint": null,
      "relativeHumidity": null,
      "windSpeed": "0 to 5 mph",
      "windDirection": "NW",
      "shortForecast": "Patchy Fog",
      "detailedForecast": "Patchy fog after 10pm. Partly cloudy, with a low around 52.",
      "isDaytime": false,
      "startTime": "2025-12-14T18:00:00-08:00",
      "endTime": "2025-12-15T06:00:00-08:00"
    },
    {
      "name": "Monday",
      "temperature": 69,
      "temperatureUnit": "F",
      "temperatureTrend": null,
      "probabilityOfPrecipitation": 0,
      "dewpoint": null,
      "relativeHumidity": null,
      "windSpeed": "0 to 5 mph",
      "windDirection": "NW",
      "shortForecast": "Patchy Fog then Mostly Sunny",
      "detailedForecast": "Patchy fog before 10am. Mostly sunny, with a high near 69.",
      "isDaytime": true,
      "startTime": "2025-12-15T06:00:00-08:00",
      "endTime": "2025-12-15T18:00:00-08:00"
    },
    {
      "name": "Monday Night",
      "temperature": 53,
      "temperatureUnit": "F",
      "temperatureTrend": null,
      "probabilityOfPrecipitation": 1,
      "dewpoint": null,
      "relativeHumidity": null,
      "windSpeed": "0 to 5 mph",
      "windDirection": "N",
      "shortForecast": "Patchy Fog",
      "detailedForecast": "Patchy fog after 10pm. Mostly cloudy, with a low around 53.",
      "isDaytime": false,
      "startTime": "2025-12-15T18:00:00-08:00",
      "endTime": "2025-12-16T06:00:00-08:00"
    },
    {
      "name": "Tuesday",
      "temperature": 68,
      "temperatureUnit": "F",
      "temperatureTrend": null,
      "probabilityOfPrecipitation": 2,
      "dewpoint": null,
      "relativeHumidity": null,
      "windSpeed": "0 to 5 mph",
      "windDirection": "NE",
      "shortForecast": "Patchy Fog then Mostly Sunny",
      "detailedForecast": "Patchy fog before 10am. Mostly sunny, with a high near 68.",
      "isDaytime": true,
      "startTime": "2025-12-16T06:00:00-08:00",
      "endTime": "2025-12-16T18:00:00-08:00"
    },
    {
      "name": "Tuesday Night",
      "temperature": 55,
      "temperatureUnit": "F",
      "temperatureTrend": null,
      "probabilityOfPrecipitation": 3,
      "dewpoint": null,
      "relativeHumidity": null,
      "windSpeed": "5 mph",
      "windDirection": "NE",
      "shortForecast": "Patchy Fog",
      "detailedForecast": "Patchy fog after 10pm. Partly cloudy, with a low around 55.",
      "isDaytime": false,
      "startTime": "2025-12-16T18:00:00-08:00",
      "endTime": "2025-12-17T06:00:00-08:00"
    }
  ]
}