{
  "location": "KOMA",
  "forecast_date": "2026-06-08",
  "target_date": "2026-06-11",
  "lead_time_days": 3,
  "open_meteo": {
    "temp_high": 85.1,
    "temp_low": 62.8,
    "precip": 0.0
  },
  "nws": [
    {
      "name": "Overnight",
      "temperature": 68,
      "temperatureUnit": "F",
      "temperatureTrend": null,
      "probabilityOfPrecipitation": 2,
      "dewpoint": null,
      "relativeHumidity": null,
      "windSpeed": "7 mph",
      "windDirection": "SE",
      "shortForecast": "Mostly Cloudy",
      "detailedForecast": "Mostly cloudy. Low around 68, with temperatures rising to around 71 overnight. Southeast wind around 7 mph.",
      "isDaytime": false,
      "startTime": "2026-06-08T04:00:00-05:00",
      "endTime": "2026-06-08T06:00:00-05:00"
    },
    {
      "name": "Monday",
      "temperature": 88,
      "temperatureUnit": "F",
      "temperatureTrend": null,
      "probabilityOfPrecipitation": 5,
      "dewpoint": null,
      "relativeHumidity": null,
      "windSpeed": "0 to 5 mph",
      "windDirection": "SSE",
      "shortForecast": "Mostly Sunny",
      "detailedForecast": "Mostly sunny, with a high near 88. South southeast wind 0 to 5 mph.",
      "isDaytime": true,
      "startTime": "2026-06-08T06:00:00-05:00",
      "endTime": "2026-06-08T18:00:00-05:00"
    },
    {
      "name": "Monday Night",
      "temperature": 70,
      "temperatureUnit": "F",
      "temperatureTrend": null,
      "probabilityOfPrecipitation": 29,
      "dewpoint": null,
      "relativeHumidity": null,
      "windSpeed": "8 mph",
      "windDirection": "SE",
      "shortForecast": "Chance Showers And Thunderstorms",
      "detailedForecast": "A chance of showers and thunderstorms between 7pm and 5am. Partly cloudy, with a low around 70. Southeast wind around 8 mph. Chance of precipitation is 30%. New rainfall amounts less than a tenth of an inch possible.",
      "isDaytime": false,
      "startTime": "2026-06-08T18:00:00-05:00",
      "endTime": "2026-06-09T06:00:00-05:00"
    },
    {
      "name": "Tuesday",
      "temperature": 95,
      "temperatureUnit": "F",
      "temperatureTrend": null,
      "probabilityOfPrecipitation": 11,
      "dewpoint": null,
      "relativeHumidity": null,
      "windSpeed": "7 to 21 mph",
      "windDirection": "SSE",
      "shortForecast": "Mostly Sunny",
      "detailedForecast": "Mostly sunny, with a high near 95. South southeast wind 7 to 21 mph, with gusts as high as 30 mph. New rainfall amounts less than a tenth of an inch possible.",
      "isDaytime": true,
      "startTime": "2026-06-09T06:00:00-05:00",
      "endTime": "2026-06-09T18:00:00-05:00"
    },
    {
      "name": "Tuesday Night",
      "temperature": 77,
      "temperatureUnit": "F",
      "temperatureTrend": null,
      "probabilityOfPrecipitation": 32,
      "dewpoint": null,
      "relativeHumidity": null,
      "windSpeed": "22 mph",
      "windDirection": "S",
      "shortForecast": "Chance Showers And Thunderstorms",
      "detailedForecast": "A chance of showers and thunderstorms between 7pm and 10pm, then a chance of showers and thunderstorms between 10pm and 1am, then a slight chance of showers and thunderstorms. Partly cloudy, with a low around 77. South wind around 22 mph, with gusts as high as 33 mph. Chance of precipitation is 30%.",
      "isDaytime": false,
      "startTime": "2026-06-09T18:00:00-05:00",
      "endTime": "2026-06-10T06:00:00-05:00"
    },
    {
      "name": "Wednesday",
      "temperature": 96,
      "temperatureUnit": "F",
      "temperatureTrend": null,
      "probabilityOfPrecipitation": 30,
      "dewpoint": null,
      "relativeHumidity": null,
      "windSpeed": "15 to 21 mph",
      "windDirection": "SW",
      "shortForecast": "Chance Showers And Thunderstorms",
      "detailedForecast": "A chance of showers and thunderstorms before 4pm, then a chance of showers and thunderstorms. Mostly sunny, with a high near 96. Southwest wind 15 to 21 mph, with gusts as high as 30 mph. Chance of precipitation is 30%. New rainfall amounts less than a tenth of an inch possible.",
      "isDaytime": true,
      "startTime": "2026-06-10T06:00:00-05:00",
      "endTime": "2026-06-10T18:00:00-05:00"
    },
    {
      "name": "Wednesday Night",
      "temperature": 67,
      "temperatureUnit": "F",
      "temperatureTrend": null,
      "probabilityOfPrecipitation": 43,
      "dewpoint": null,
      "relativeHumidity": null,
      "windSpeed": "6 to 14 mph",
      "windDirection": "SSW",
      "shortForecast": "Chance Showers And Thunderstorms",
      "detailedForecast": "A chance of showers and thunderstorms before 10pm, then a chance of showers and thunderstorms. Mostly clear, with a low around 67. South southwest wind 6 to 14 mph, with gusts as high as 20 mph.",
      "isDaytime": false,
      "startTime": "2026-06-10T18:00:00-05:00",
      "endTime": "2026-06-11T06:00:00-05:00"
    },
    {
      "name": "Thursday",
      "temperature": 88,
      "temperatureUnit": "F",
      "temperatureTrend": null,
      "probabilityOfPrecipitation": 43,
      "dewpoint": null,
      "relativeHumidity": null,
      "windSpeed": "7 to 16 mph",
      "windDirection": "WNW",
      "shortForecast": "Chance Showers And Thunderstorms then Sunny",
      "detailedForecast": "A chance of showers and thunderstorms before 7am. Sunny, with a high near 88. West northwest wind 7 to 16 mph, with gusts as high as 23 mph.",
      "isDaytime": true,
      "startTime": "2026-06-11T06:00:00-05:00",
      "endTime": "2026-06-11T18:00:00-05:00"
    },
    {
      "name": "Thursday Night",
      "temperature": 62,
      "temperatureUnit": "F",
      "temperatureTrend": null,
      "probabilityOfPrecipitation": 9,
      "dewpoint": null,
      "relativeHumidity": null,
      "windSpeed": "2 to 14 mph",
      "windDirection": "WNW",
      "shortForecast": "Mostly Clear",
      "detailedForecast": "Mostly clear, with a low around 62. West northwest wind 2 to 14 mph.",
      "isDaytime": false,
      "startTime": "2026-06-11T18:00:00-05:00",
      "endTime": "2026-06-12T06:00:00-05:00"
    },
    {
      "name": "Friday",
      "temperature": 89,
      "temperatureUnit": "F",
      "temperatureTrend": null,
      "probabilityOfPrecipitation": 22,
      "dewpoint": null,
      "relativeHumidity": null,
      "windSpeed": "3 to 10 mph",
      "windDirection": "SSW",
      "shortForecast": "Sunny then Slight Chance Rain Showers",
      "detailedForecast": "A slight chance of rain showers after 1pm. Sunny, with a high near 89. South southwest wind 3 to 10 mph, with gusts as high as 20 mph.",
      "isDaytime": true,
      "startTime": "2026-06-12T06:00:00-05:00",
      "endTime": "2026-06-12T18:00:00-05:00"
    },
    {
      "name": "Friday Night",
      "temperature": 65,
      "temperatureUnit": "F",
      "temperatureTrend": null,
      "probabilityOfPrecipitation": 30,
      "dewpoint": null,
      "relativeHumidity": null,
      "windSpeed": "5 to 9 mph",
      "windDirection": "S",
      "shortForecast": "Chance Showers And Thunderstorms",
      "detailedForecast": "A slight chance of rain showers before 7pm, then a chance of showers and thunderstorms between 7pm and 1am, then a slight chance of showers and thunderstorms. Mostly clear, with a low around 65. South wind 5 to 9 mph, with gusts as high as 17 mph.",
      "isDaytime": false,
      "startTime": "2026-06-12T18:00:00-05:00",
      "endTime": "2026-06-13T06:00:00-05:00"
    },
    {
      "name": "Saturday",
      "temperature": 86,
      "temperatureUnit": "F",
      "temperatureTrend": null,
      "probabilityOfPrecipitation": 50,
      "dewpoint": null,
      "relativeHumidity": null,
      "windSpeed": "6 to 9 mph",
      "windDirection": "SE",
      "shortForecast": "Chance Showers And Thunderstorms",
      "detailedForecast": "A chance of showers and thunderstorms. Mostly sunny, with a high near 86. Southeast wind 6 to 9 mph, with gusts as high as 17 mph.",
      "isDaytime": true,
      "startTime": "2026-06-13T06:00:00-05:00",
      "endTime": "2026-06-13T18:00:00-05:00"
    },
    {
      "name": "Saturday Night",
      "temperature": 62,
      "temperatureUnit": "F",
      "temperatureTrend": null,
      "probabilityOfPrecipitation": 50,
      "dewpoint": null,
      "relativeHumidity": null,
      "windSpeed": "5 to 9 mph",
      "windDirection": "NNE",
      "shortForecast": "Chance Showers And Thunderstorms",
      "detailedForecast": "A chance of showers and thunderstorms. Partly cloudy, with a low around 62. North northeast wind 5 to 9 mph, with gusts as high as 16 mph.",
      "isDaytime": false,
      "startTime": "2026-06-13T18:00:00-05:00",
      "endTime": "2026-06-14T06:00:00-05:00"
    },
    {
      "name": "Sunday",
      "temperature": 80,
      "temperatureUnit": "F",
      "temperatureTrend": null,
      "probabilityOfPrecipitation": 19,
      "dewpoint": null,
      "relativeHumidity": null,
      "windSpeed": "6 to 9 mph",
      "windDirection": "NNE",
      "shortForecast": "Slight Chance Showers And Thunderstorms",
      "detailedForecast": "A slight chance of showers and thunderstorms. Mostly sunny, with a high near 80. North northeast wind 6 to 9 mph, with gusts as high as 18 mph.",
      "isDaytime": true,
      "startTime": "2026-06-14T06:00:00-05:00",
      "endTime": "2026-06-14T18:00:00-05:00"
    }
  ]
}