{
  "location": "KORD",
  "forecast_date": "2026-02-15",
  "target_date": "2026-02-22",
  "lead_time_days": 7,
  "open_meteo": {
    "temp_high": 33.3,
    "temp_low": 23.7,
    "precip": 0.0
  },
  "nws": [
    {
      "name": "Overnight",
      "temperature": 35,
      "temperatureUnit": "F",
      "temperatureTrend": null,
      "probabilityOfPrecipitation": 2,
      "dewpoint": null,
      "relativeHumidity": null,
      "windSpeed": "5 mph",
      "windDirection": "SW",
      "shortForecast": "Mostly Cloudy",
      "detailedForecast": "Mostly cloudy, with a low around 35. Southwest wind around 5 mph, with gusts as high as 10 mph.",
      "isDaytime": false,
      "startTime": "2026-02-15T00:00:00-06:00",
      "endTime": "2026-02-15T06:00:00-06:00"
    },
    {
      "name": "Sunday",
      "temperature": 57,
      "temperatureUnit": "F",
      "temperatureTrend": null,
      "probabilityOfPrecipitation": 0,
      "dewpoint": null,
      "relativeHumidity": null,
      "windSpeed": "5 to 10 mph",
      "windDirection": "WNW",
      "shortForecast": "Sunny",
      "detailedForecast": "Sunny. High near 57, with temperatures falling to around 53 in the afternoon. West northwest wind 5 to 10 mph.",
      "isDaytime": true,
      "startTime": "2026-02-15T06:00:00-06:00",
      "endTime": "2026-02-15T18:00:00-06:00"
    },
    {
      "name": "Sunday Night",
      "temperature": 35,
      "temperatureUnit": "F",
      "temperatureTrend": null,
      "probabilityOfPrecipitation": 0,
      "dewpoint": null,
      "relativeHumidity": null,
      "windSpeed": "5 mph",
      "windDirection": "SE",
      "shortForecast": "Partly Cloudy",
      "detailedForecast": "Partly cloudy. Low around 35, with temperatures rising to around 37 overnight. Southeast wind around 5 mph, with gusts as high as 15 mph.",
      "isDaytime": false,
      "startTime": "2026-02-15T18:00:00-06:00",
      "endTime": "2026-02-16T06:00:00-06:00"
    },
    {
      "name": "Washington's Birthday",
      "temperature": 60,
      "temperatureUnit": "F",
      "temperatureTrend": null,
      "probabilityOfPrecipitation": 0,
      "dewpoint": null,
      "relativeHumidity": null,
      "windSpeed": "10 to 15 mph",
      "windDirection": "SW",
      "shortForecast": "Mostly Sunny",
      "detailedForecast": "Mostly sunny, with a high near 60. Southwest wind 10 to 15 mph, with gusts as high as 30 mph.",
      "isDaytime": true,
      "startTime": "2026-02-16T06:00:00-06:00",
      "endTime": "2026-02-16T18:00:00-06:00"
    },
    {
      "name": "Monday Night",
      "temperature": 39,
      "temperatureUnit": "F",
      "temperatureTrend": null,
      "probabilityOfPrecipitation": 0,
      "dewpoint": null,
      "relativeHumidity": null,
      "windSpeed": "5 mph",
      "windDirection": "S",
      "shortForecast": "Mostly Cloudy",
      "detailedForecast": "Mostly cloudy, with a low around 39. South wind around 5 mph, with gusts as high as 15 mph.",
      "isDaytime": false,
      "startTime": "2026-02-16T18:00:00-06:00",
      "endTime": "2026-02-17T06:00:00-06:00"
    },
    {
      "name": "Tuesday",
      "temperature": 48,
      "temperatureUnit": "F",
      "temperatureTrend": null,
      "probabilityOfPrecipitation": 5,
      "dewpoint": null,
      "relativeHumidity": null,
      "windSpeed": "5 to 15 mph",
      "windDirection": "ESE",
      "shortForecast": "Mostly Cloudy",
      "detailedForecast": "Mostly cloudy, with a high near 48.",
      "isDaytime": true,
      "startTime": "2026-02-17T06:00:00-06:00",
      "endTime": "2026-02-17T18:00:00-06:00"
    },
    {
      "name": "Tuesday Night",
      "temperature": 45,
      "temperatureUnit": "F",
      "temperatureTrend": null,
      "probabilityOfPrecipitation": 39,
      "dewpoint": null,
      "relativeHumidity": null,
      "windSpeed": "15 mph",
      "windDirection": "SSE",
      "shortForecast": "Chance Showers And Thunderstorms",
      "detailedForecast": "A slight chance of rain showers before midnight, then a chance of showers and thunderstorms. Mostly cloudy, with a low around 45.",
      "isDaytime": false,
      "startTime": "2026-02-17T18:00:00-06:00",
      "endTime": "2026-02-18T06:00:00-06:00"
    },
    {
      "name": "Wednesday",
      "temperature": 64,
      "temperatureUnit": "F",
      "temperatureTrend": null,
      "probabilityOfPrecipitation": 26,
      "dewpoint": null,
      "relativeHumidity": null,
      "windSpeed": "15 to 25 mph",
      "windDirection": "SW",
      "shortForecast": "Chance Showers And Thunderstorms then Sunny",
      "detailedForecast": "A chance of showers and thunderstorms before noon. Sunny, with a high near 64.",
      "isDaytime": true,
      "startTime": "2026-02-18T06:00:00-06:00",
      "endTime": "2026-02-18T18:00:00-06:00"
    },
    {
      "name": "Wednesday Night",
      "temperature": 39,
      "temperatureUnit": "F",
      "temperatureTrend": null,
      "probabilityOfPrecipitation": 14,
      "dewpoint": null,
      "relativeHumidity": null,
      "windSpeed": "5 to 15 mph",
      "windDirection": "W",
      "shortForecast": "Mostly Clear",
      "detailedForecast": "Mostly clear, with a low around 39.",
      "isDaytime": false,
      "startTime": "2026-02-18T18:00:00-06:00",
      "endTime": "2026-02-19T06:00:00-06:00"
    },
    {
      "name": "Thursday",
      "temperature": 51,
      "temperatureUnit": "F",
      "temperatureTrend": null,
      "probabilityOfPrecipitation": 26,
      "dewpoint": null,
      "relativeHumidity": null,
      "windSpeed": "5 to 10 mph",
      "windDirection": "NE",
      "shortForecast": "Mostly Sunny then Chance Rain Showers",
      "detailedForecast": "A chance of rain showers after noon. Mostly sunny, with a high near 51.",
      "isDaytime": true,
      "startTime": "2026-02-19T06:00:00-06:00",
      "endTime": "2026-02-19T18:00:00-06:00"
    },
    {
      "name": "Thursday Night",
      "temperature": 32,
      "temperatureUnit": "F",
      "temperatureTrend": null,
      "probabilityOfPrecipitation": 36,
      "dewpoint": null,
      "relativeHumidity": null,
      "windSpeed": "10 to 15 mph",
      "windDirection": "NNE",
      "shortForecast": "Chance Rain Showers",
      "detailedForecast": "A chance of rain showers. Mostly cloudy, with a low around 32.",
      "isDaytime": false,
      "startTime": "2026-02-19T18:00:00-06:00",
      "endTime": "2026-02-20T06:00:00-06:00"
    },
    {
      "name": "Friday",
      "temperature": 42,
      "temperatureUnit": "F",
      "temperatureTrend": null,
      "probabilityOfPrecipitation": 25,
      "dewpoint": null,
      "relativeHumidity": null,
      "windSpeed": "15 mph",
      "windDirection": "WNW",
      "shortForecast": "Chance Rain Showers",
      "detailedForecast": "A chance of rain showers. Partly sunny, with a high near 42.",
      "isDaytime": true,
      "startTime": "2026-02-20T06:00:00-06:00",
      "endTime": "2026-02-20T18:00:00-06:00"
    },
    {
      "name": "Friday Night",
      "temperature": 26,
      "temperatureUnit": "F",
      "temperatureTrend": null,
      "probabilityOfPrecipitation": 21,
      "dewpoint": null,
      "relativeHumidity": null,
      "windSpeed": "10 mph",
      "windDirection": "WNW",
      "shortForecast": "Slight Chance Rain And Snow Showers",
      "detailedForecast": "A slight chance of rain and snow showers. Mostly cloudy, with a low around 26.",
      "isDaytime": false,
      "startTime": "2026-02-20T18:00:00-06:00",
      "endTime": "2026-02-21T06:00:00-06:00"
    },
    {
      "name": "Saturday",
      "temperature": 38,
      "temperatureUnit": "F",
      "temperatureTrend": null,
      "probabilityOfPrecipitation": 15,
      "dewpoint": null,
      "relativeHumidity": null,
      "windSpeed": "10 mph",
      "windDirection": "WNW",
      "shortForecast": "Partly Sunny then Slight Chance Rain And Snow Showers",
      "detailedForecast": "A slight chance of rain and snow showers after noon. Partly sunny, with a high near 38.",
      "isDaytime": true,
      "startTime": "2026-02-21T06:00:00-06:00",
      "endTime": "2026-02-21T18:00:00-06:00"
    }
  ]
}