{
  "location": "KORD",
  "forecast_date": "2025-11-06",
  "target_date": "2025-11-09",
  "lead_time_days": 3,
  "open_meteo": {
    "temp_high": 36.6,
    "temp_low": 29.9,
    "precip": 0.008
  },
  "nws": [
    {
      "name": "Overnight",
      "temperature": 37,
      "temperatureUnit": "F",
      "temperatureTrend": "",
      "probabilityOfPrecipitation": 0,
      "dewpoint": null,
      "relativeHumidity": null,
      "windSpeed": "5 mph",
      "windDirection": "WNW",
      "shortForecast": "Partly Cloudy",
      "detailedForecast": "Partly cloudy, with a low around 37. West northwest wind around 5 mph.",
      "isDaytime": false,
      "startTime": "2025-11-06T02:00:00-06:00",
      "endTime": "2025-11-06T06:00:00-06:00"
    },
    {
      "name": "Thursday",
      "temperature": 58,
      "temperatureUnit": "F",
      "temperatureTrend": "",
      "probabilityOfPrecipitation": 0,
      "dewpoint": null,
      "relativeHumidity": null,
      "windSpeed": "0 to 10 mph",
      "windDirection": "SSW",
      "shortForecast": "Mostly Sunny",
      "detailedForecast": "Mostly sunny. High near 58, with temperatures falling to around 54 in the afternoon. South southwest wind 0 to 10 mph, with gusts as high as 20 mph.",
      "isDaytime": true,
      "startTime": "2025-11-06T06:00:00-06:00",
      "endTime": "2025-11-06T18:00:00-06:00"
    },
    {
      "name": "Thursday Night",
      "temperature": 49,
      "temperatureUnit": "F",
      "temperatureTrend": "",
      "probabilityOfPrecipitation": 91,
      "dewpoint": null,
      "relativeHumidity": null,
      "windSpeed": "10 to 15 mph",
      "windDirection": "SSW",
      "shortForecast": "Showers And Thunderstorms",
      "detailedForecast": "A slight chance of rain showers between 9pm and midnight, then showers and thunderstorms. Cloudy, with a low around 49. South southwest wind 10 to 15 mph, with gusts as high as 35 mph. Chance of precipitation is 90%. New rainfall amounts between a tenth and quarter of an inch possible.",
      "isDaytime": false,
      "startTime": "2025-11-06T18:00:00-06:00",
      "endTime": "2025-11-07T06:00:00-06:00"
    },
    {
      "name": "Friday",
      "temperature": 63,
      "temperatureUnit": "F",
      "temperatureTrend": "",
      "probabilityOfPrecipitation": 16,
      "dewpoint": null,
      "relativeHumidity": null,
      "windSpeed": "10 to 15 mph",
      "windDirection": "WSW",
      "shortForecast": "Slight Chance Rain Showers then Mostly Sunny",
      "detailedForecast": "A slight chance of rain showers before noon. Mostly sunny, with a high near 63. West southwest wind 10 to 15 mph, with gusts as high as 30 mph. Chance of precipitation is 20%.",
      "isDaytime": true,
      "startTime": "2025-11-07T06:00:00-06:00",
      "endTime": "2025-11-07T18:00:00-06:00"
    },
    {
      "name": "Friday Night",
      "temperature": 39,
      "temperatureUnit": "F",
      "temperatureTrend": "",
      "probabilityOfPrecipitation": 17,
      "dewpoint": null,
      "relativeHumidity": null,
      "windSpeed": "5 to 10 mph",
      "windDirection": "NW",
      "shortForecast": "Slight Chance Rain Showers then Partly Cloudy",
      "detailedForecast": "A slight chance of rain showers before midnight. Partly cloudy, with a low around 39. Northwest wind 5 to 10 mph, with gusts as high as 20 mph. Chance of precipitation is 20%.",
      "isDaytime": false,
      "startTime": "2025-11-07T18:00:00-06:00",
      "endTime": "2025-11-08T06:00:00-06:00"
    },
    {
      "name": "Saturday",
      "temperature": 51,
      "temperatureUnit": "F",
      "temperatureTrend": "",
      "probabilityOfPrecipitation": 67,
      "dewpoint": null,
      "relativeHumidity": null,
      "windSpeed": "5 to 10 mph",
      "windDirection": "NNE",
      "shortForecast": "Rain Likely",
      "detailedForecast": "Rain likely. Mostly cloudy, with a high near 51. Chance of precipitation is 70%.",
      "isDaytime": true,
      "startTime": "2025-11-08T06:00:00-06:00",
      "endTime": "2025-11-08T18:00:00-06:00"
    },
    {
      "name": "Saturday Night",
      "temperature": 32,
      "temperatureUnit": "F",
      "temperatureTrend": "",
      "probabilityOfPrecipitation": 83,
      "dewpoint": null,
      "relativeHumidity": null,
      "windSpeed": "10 to 15 mph",
      "windDirection": "N",
      "shortForecast": "Rain then Rain And Snow Likely",
      "detailedForecast": "Rain before 3am, then rain and snow likely. Mostly cloudy, with a low around 32. New snow accumulation of less than half an inch possible.",
      "isDaytime": false,
      "startTime": "2025-11-08T18:00:00-06:00",
      "endTime": "2025-11-09T06:00:00-06:00"
    },
    {
      "name": "Sunday",
      "temperature": 36,
      "temperatureUnit": "F",
      "temperatureTrend": "",
      "probabilityOfPrecipitation": 38,
      "dewpoint": null,
      "relativeHumidity": null,
      "windSpeed": "15 to 20 mph",
      "windDirection": "NW",
      "shortForecast": "Chance Rain And Snow",
      "detailedForecast": "A chance of rain and snow. Partly sunny, with a high near 36.",
      "isDaytime": true,
      "startTime": "2025-11-09T06:00:00-06:00",
      "endTime": "2025-11-09T18:00:00-06:00"
    },
    {
      "name": "Sunday Night",
      "temperature": 24,
      "temperatureUnit": "F",
      "temperatureTrend": "",
      "probabilityOfPrecipitation": 34,
      "dewpoint": null,
      "relativeHumidity": null,
      "windSpeed": "15 mph",
      "windDirection": "NW",
      "shortForecast": "Chance Snow Showers",
      "detailedForecast": "A chance of snow showers. Partly cloudy, with a low around 24.",
      "isDaytime": false,
      "startTime": "2025-11-09T18:00:00-06:00",
      "endTime": "2025-11-10T06:00:00-06:00"
    },
    {
      "name": "Monday",
      "temperature": 37,
      "temperatureUnit": "F",
      "temperatureTrend": "",
      "probabilityOfPrecipitation": 20,
      "dewpoint": null,
      "relativeHumidity": null,
      "windSpeed": "10 to 15 mph",
      "windDirection": "NW",
      "shortForecast": "Slight Chance Snow Showers then Mostly Sunny",
      "detailedForecast": "A slight chance of snow showers before noon. Mostly sunny, with a high near 37.",
      "isDaytime": true,
      "startTime": "2025-11-10T06:00:00-06:00",
      "endTime": "2025-11-10T18:00:00-06:00"
    },
    {
      "name": "Monday Night",
      "temperature": 26,
      "temperatureUnit": "F",
      "temperatureTrend": "",
      "probabilityOfPrecipitation": 7,
      "dewpoint": null,
      "relativeHumidity": null,
      "windSpeed": "10 mph",
      "windDirection": "WSW",
      "shortForecast": "Partly Cloudy",
      "detailedForecast": "Partly cloudy, with a low around 26.",
      "isDaytime": false,
      "startTime": "2025-11-10T18:00:00-06:00",
      "endTime": "2025-11-11T06:00:00-06:00"
    },
    {
      "name": "Veterans Day",
      "temperature": 48,
      "temperatureUnit": "F",
      "temperatureTrend": "",
      "probabilityOfPrecipitation": 6,
      "dewpoint": null,
      "relativeHumidity": null,
      "windSpeed": "10 to 15 mph",
      "windDirection": "SW",
      "shortForecast": "Partly Sunny",
      "detailedForecast": "Partly sunny, with a high near 48.",
      "isDaytime": true,
      "startTime": "2025-11-11T06:00:00-06:00",
      "endTime": "2025-11-11T18:00:00-06:00"
    },
    {
      "name": "Tuesday Night",
      "temperature": 37,
      "temperatureUnit": "F",
      "temperatureTrend": "",
      "probabilityOfPrecipitation": 3,
      "dewpoint": null,
      "relativeHumidity": null,
      "windSpeed": "10 to 15 mph",
      "windDirection": "WSW",
      "shortForecast": "Partly Cloudy",
      "detailedForecast": "Partly cloudy, with a low around 37.",
      "isDaytime": false,
      "startTime": "2025-11-11T18:00:00-06:00",
      "endTime": "2025-11-12T06:00:00-06:00"
    },
    {
      "name": "Wednesday",
      "temperature": 53,
      "temperatureUnit": "F",
      "temperatureTrend": "",
      "probabilityOfPrecipitation": 2,
      "dewpoint": null,
      "relativeHumidity": null,
      "windSpeed": "10 to 15 mph",
      "windDirection": "W",
      "shortForecast": "Mostly Sunny",
      "detailedForecast": "Mostly sunny, with a high near 53.",
      "isDaytime": true,
      "startTime": "2025-11-12T06:00:00-06:00",
      "endTime": "2025-11-12T18:00:00-06:00"
    }
  ]
}