{
  "location": "KPHX",
  "forecast_date": "2026-03-17",
  "target_date": "2026-04-01",
  "lead_time_days": 15,
  "open_meteo": {
    "temp_high": null,
    "temp_low": null,
    "precip": null
  },
  "nws": [
    {
      "name": "Overnight",
      "temperature": 66,
      "temperatureUnit": "F",
      "temperatureTrend": null,
      "probabilityOfPrecipitation": 0,
      "dewpoint": null,
      "relativeHumidity": null,
      "windSpeed": "5 mph",
      "windDirection": "ENE",
      "shortForecast": "Mostly Clear",
      "detailedForecast": "Mostly clear. Low around 66, with temperatures rising to around 68 overnight. East northeast wind around 5 mph.",
      "isDaytime": false,
      "startTime": "2026-03-17T01:00:00-07:00",
      "endTime": "2026-03-17T06:00:00-07:00"
    },
    {
      "name": "Tuesday",
      "temperature": 96,
      "temperatureUnit": "F",
      "temperatureTrend": null,
      "probabilityOfPrecipitation": 0,
      "dewpoint": null,
      "relativeHumidity": null,
      "windSpeed": "5 to 10 mph",
      "windDirection": "NNE",
      "shortForecast": "Sunny",
      "detailedForecast": "Sunny, with a high near 96. North northeast wind 5 to 10 mph.",
      "isDaytime": true,
      "startTime": "2026-03-17T06:00:00-07:00",
      "endTime": "2026-03-17T18:00:00-07:00"
    },
    {
      "name": "Tuesday Night",
      "temperature": 68,
      "temperatureUnit": "F",
      "temperatureTrend": null,
      "probabilityOfPrecipitation": 0,
      "dewpoint": null,
      "relativeHumidity": null,
      "windSpeed": "5 mph",
      "windDirection": "NE",
      "shortForecast": "Clear",
      "detailedForecast": "Clear, with a low around 68. Northeast wind around 5 mph.",
      "isDaytime": false,
      "startTime": "2026-03-17T18:00:00-07:00",
      "endTime": "2026-03-18T06:00:00-07:00"
    },
    {
      "name": "Wednesday",
      "temperature": 102,
      "temperatureUnit": "F",
      "temperatureTrend": null,
      "probabilityOfPrecipitation": 0,
      "dewpoint": null,
      "relativeHumidity": null,
      "windSpeed": "5 to 10 mph",
      "windDirection": "SSE",
      "shortForecast": "Sunny",
      "detailedForecast": "Sunny, with a high near 102. South southeast wind 5 to 10 mph.",
      "isDaytime": true,
      "startTime": "2026-03-18T06:00:00-07:00",
      "endTime": "2026-03-18T18:00:00-07:00"
    },
    {
      "name": "Wednesday Night",
      "temperature": 69,
      "temperatureUnit": "F",
      "temperatureTrend": null,
      "probabilityOfPrecipitation": 0,
      "dewpoint": null,
      "relativeHumidity": null,
      "windSpeed": "5 to 10 mph",
      "windDirection": "N",
      "shortForecast": "Mostly Clear",
      "detailedForecast": "Mostly clear, with a low around 69. North wind 5 to 10 mph.",
      "isDaytime": false,
      "startTime": "2026-03-18T18:00:00-07:00",
      "endTime": "2026-03-19T06:00:00-07:00"
    },
    {
      "name": "Thursday",
      "temperature": 105,
      "temperatureUnit": "F",
      "temperatureTrend": null,
      "probabilityOfPrecipitation": 0,
      "dewpoint": null,
      "relativeHumidity": null,
      "windSpeed": "5 mph",
      "windDirection": "SSW",
      "shortForecast": "Sunny",
      "detailedForecast": "Sunny, with a high near 105. South southwest wind around 5 mph.",
      "isDaytime": true,
      "startTime": "2026-03-19T06:00:00-07:00",
      "endTime": "2026-03-19T18:00:00-07:00"
    },
    {
      "name": "Thursday Night",
      "temperature": 71,
      "temperatureUnit": "F",
      "temperatureTrend": null,
      "probabilityOfPrecipitation": 0,
      "dewpoint": null,
      "relativeHumidity": null,
      "windSpeed": "5 mph",
      "windDirection": "NNE",
      "shortForecast": "Clear",
      "detailedForecast": "Clear, with a low around 71. North northeast wind around 5 mph.",
      "isDaytime": false,
      "startTime": "2026-03-19T18:00:00-07:00",
      "endTime": "2026-03-20T06:00:00-07:00"
    },
    {
      "name": "Friday",
      "temperature": 106,
      "temperatureUnit": "F",
      "temperatureTrend": null,
      "probabilityOfPrecipitation": 0,
      "dewpoint": null,
      "relativeHumidity": null,
      "windSpeed": "5 mph",
      "windDirection": "SSE",
      "shortForecast": "Sunny",
      "detailedForecast": "Sunny, with a high near 106. South southeast wind around 5 mph.",
      "isDaytime": true,
      "startTime": "2026-03-20T06:00:00-07:00",
      "endTime": "2026-03-20T18:00:00-07:00"
    },
    {
      "name": "Friday Night",
      "temperature": 71,
      "temperatureUnit": "F",
      "temperatureTrend": null,
      "probabilityOfPrecipitation": 0,
      "dewpoint": null,
      "relativeHumidity": null,
      "windSpeed": "0 to 5 mph",
      "windDirection": "NNW",
      "shortForecast": "Clear",
      "detailedForecast": "Clear, with a low around 71. North northwest wind 0 to 5 mph.",
      "isDaytime": false,
      "startTime": "2026-03-20T18:00:00-07:00",
      "endTime": "2026-03-21T06:00:00-07:00"
    },
    {
      "name": "Saturday",
      "temperature": 106,
      "temperatureUnit": "F",
      "temperatureTrend": null,
      "probabilityOfPrecipitation": 0,
      "dewpoint": null,
      "relativeHumidity": null,
      "windSpeed": "0 to 5 mph",
      "windDirection": "SSE",
      "shortForecast": "Sunny",
      "detailedForecast": "Sunny, with a high near 106. South southeast wind 0 to 5 mph.",
      "isDaytime": true,
      "startTime": "2026-03-21T06:00:00-07:00",
      "endTime": "2026-03-21T18:00:00-07:00"
    },
    {
      "name": "Saturday Night",
      "temperature": 71,
      "temperatureUnit": "F",
      "temperatureTrend": null,
      "probabilityOfPrecipitation": 0,
      "dewpoint": null,
      "relativeHumidity": null,
      "windSpeed": "0 to 5 mph",
      "windDirection": "WSW",
      "shortForecast": "Clear",
      "detailedForecast": "Clear, with a low around 71. West southwest wind 0 to 5 mph.",
      "isDaytime": false,
      "startTime": "2026-03-21T18:00:00-07:00",
      "endTime": "2026-03-22T06:00:00-07:00"
    },
    {
      "name": "Sunday",
      "temperature": 103,
      "temperatureUnit": "F",
      "temperatureTrend": null,
      "probabilityOfPrecipitation": 0,
      "dewpoint": null,
      "relativeHumidity": null,
      "windSpeed": "0 to 5 mph",
      "windDirection": "SE",
      "shortForecast": "Sunny",
      "detailedForecast": "Sunny, with a high near 103. Southeast wind 0 to 5 mph.",
      "isDaytime": true,
      "startTime": "2026-03-22T06:00:00-07:00",
      "endTime": "2026-03-22T18:00:00-07:00"
    },
    {
      "name": "Sunday Night",
      "temperature": 70,
      "temperatureUnit": "F",
      "temperatureTrend": null,
      "probabilityOfPrecipitation": 0,
      "dewpoint": null,
      "relativeHumidity": null,
      "windSpeed": "0 to 5 mph",
      "windDirection": "S",
      "shortForecast": "Partly Cloudy",
      "detailedForecast": "Partly cloudy, with a low around 70. South wind 0 to 5 mph.",
      "isDaytime": false,
      "startTime": "2026-03-22T18:00:00-07:00",
      "endTime": "2026-03-23T06:00:00-07:00"
    },
    {
      "name": "Monday",
      "temperature": 100,
      "temperatureUnit": "F",
      "temperatureTrend": null,
      "probabilityOfPrecipitation": 0,
      "dewpoint": null,
      "relativeHumidity": null,
      "windSpeed": "0 to 5 mph",
      "windDirection": "S",
      "shortForecast": "Sunny",
      "detailedForecast": "Sunny, with a high near 100. South wind 0 to 5 mph.",
      "isDaytime": true,
      "startTime": "2026-03-23T06:00:00-07:00",
      "endTime": "2026-03-23T18:00:00-07:00"
    }
  ]
}